{
  "pix_points": [
    [637, 375],
    [339, 190],
    [366, 445],
    [979, 405],
    [1130, 241],
    [184, 117],
    [402, 355],
    [820, 357],
    [647, 343]
  ],
  "robot_points": [
    [351.76,15.46],
    [265.41,-141.83],
    [397.01,-122.59],
    [356.67,198.54],
    [267.71,269.33],
    [232.73,-224.39],
    [350.02,-106.35],
    [336.82,113.56],
    [336.06,20.99]
  ],
  "cap_to_keyboard": 486,
  "robot_on_keyboard": -86.73,
  "press_deep": 4,
  "init_pos": {
    "pos_x": 265.11,
    "pos_y":-122.32,
    "pos_z": -3.79
  }
}